ivolatility_backtesting/__init__.py
ivolatility_backtesting/ivolatility_backtesting.py
ivolatility_backtesting-1.42.dist-info/licenses/LICENSE
ivolatility_backtesting-1.42.dist-info/METADATA
ivolatility_backtesting-1.42.dist-info/WHEEL
ivolatility_backtesting-1.42.dist-info/top_level.txt
ivolatility_backtesting-1.42.dist-info/RECORD
