Metadata-Version: 2.4
Name: ivolatility_backtesting
Version: 1.42
Summary: A universal backtesting framework for financial strategies using the IVolatility API.
Author-email: IVolatility <support@ivolatility.com>
Project-URL: Homepage, https://ivolatility.com
Keywords: backtesting,finance,trading,ivolatility
Classifier: Programming Language :: Python :: 3
Classifier: Programming Language :: Python :: 3.8
Classifier: Programming Language :: Python :: 3.9
Classifier: Programming Language :: Python :: 3.10
Classifier: Programming Language :: Python :: 3.11
Classifier: Programming Language :: Python :: 3.12
Classifier: License :: OSI Approved :: MIT License
Classifier: Operating System :: OS Independent
Requires-Python: >=3.8
License-File: LICENSE
Requires-Dist: pandas>=1.5.0
Requires-Dist: numpy>=1.21.0
Requires-Dist: matplotlib>=3.5.0
Requires-Dist: seaborn>=0.11.0
Requires-Dist: ivolatility>=1.8.2
Requires-Dist: psutil>=7.1.0
Dynamic: license-file
